{"nodes": [{"id": "render_yaml_deploy", "label": "render.yaml (Render deployment config)", "file_type": "document", "source_file": "render.yaml", "source_location": "1-68", "source_url": null, "captured_at": null, "author": null, "contributor": null}, {"id": "concept_fallback_allow", "label": "FALLBACK_ALLOW (server key sharing option)", "file_type": "concept", "source_file": "render.yaml", "source_location": "57-59", "source_url": null, "captured_at": null, "author": null, "contributor": null}], "edges": [{"source": "render_yaml_deploy", "target": "main_app", "relation": "references", "confidence": "EXTRACTED", "confidence_score": 1.0, "source_file": "render.yaml", "source_location": "8", "weight": 1.0}, {"source": "concept_fallback_allow", "target": "render_yaml_deploy", "relation": "references", "confidence": "EXTRACTED", "confidence_score": 1.0, "source_file": "render.yaml", "source_location": "57-59", "weight": 1.0}], "hyperedges": []}